manim_voiceover_qwen3_tts/__init__.py
manim_voiceover_qwen3_tts/services/__init__.py
manim_voiceover_qwen3_tts/services/qwen3.py
manim_voiceover_qwen3_tts-0.1.1.dist-info/METADATA
manim_voiceover_qwen3_tts-0.1.1.dist-info/WHEEL
manim_voiceover_qwen3_tts-0.1.1.dist-info/entry_points.txt
manim_voiceover_qwen3_tts-0.1.1.dist-info/licenses/LICENSE
manim_voiceover_qwen3_tts-0.1.1.dist-info/RECORD
