Metadata-Version: 2.4
Name: manim-voiceover-qwen3-tts
Version: 0.1.1
Summary: Qwen3-TTS speech services for manim-voiceover: voice cloning, voice design, and preset voices
Project-URL: Homepage, https://github.com/DurhamSmith/manim-voiceover-qwen3-tts
Project-URL: Documentation, https://github.com/DurhamSmith/manim-voiceover-qwen3-tts#readme
Project-URL: Repository, https://github.com/DurhamSmith/manim-voiceover-qwen3-tts
Project-URL: Issues, https://github.com/DurhamSmith/manim-voiceover-qwen3-tts/issues
Author-email: Your Name <your.email@example.com>
License-Expression: MIT
License-File: LICENSE
Keywords: animation,manim,manim-voiceover,qwen3,qwen3-tts,speech-synthesis,text-to-speech,tts,voice-cloning,voice-design,voiceover
Classifier: Development Status :: 4 - Beta
Classifier: License :: OSI Approved :: MIT License
Classifier: Programming Language :: Python :: 3.10
Classifier: Programming Language :: Python :: 3.11
Classifier: Programming Language :: Python :: 3.12
Classifier: Topic :: Multimedia :: Sound/Audio :: Speech
Classifier: Topic :: Multimedia :: Video
Classifier: Topic :: Scientific/Engineering
Classifier: Topic :: Scientific/Engineering :: Artificial Intelligence
Requires-Python: >=3.10
Requires-Dist: manim-voiceover>=0.3.0
Requires-Dist: pydub>=0.25.1
Requires-Dist: qwen-tts>=0.0.5
Requires-Dist: scipy>=1.10.0
Requires-Dist: soundfile>=0.12.0
Provides-Extra: dev
Requires-Dist: black>=23.0; extra == 'dev'
Requires-Dist: isort>=5.12; extra == 'dev'
Requires-Dist: mypy>=1.0; extra == 'dev'
Requires-Dist: pytest-cov>=4.0; extra == 'dev'
Requires-Dist: pytest>=7.0; extra == 'dev'
Provides-Extra: flash-attn
Requires-Dist: flash-attn>=2.0.0; extra == 'flash-attn'
